LICENSE
MANIFEST.in
README.md
django_settings_view_as_json.py
requirements.txt
setup.py
django_settings_view_as_json.egg-info/PKG-INFO
django_settings_view_as_json.egg-info/SOURCES.txt
django_settings_view_as_json.egg-info/dependency_links.txt
django_settings_view_as_json.egg-info/requires.txt
django_settings_view_as_json.egg-info/top_level.txt