Metadata-Version: 1.1
Name: django-settings-view-as-json
Version: 0.0.9
Summary: View Django Settings at a URL
Home-page: https://github.com/hampsterx/django-settings-view-as-json
Author: Tim van der Hulst
Author-email: tim.vdh@gmail.com
License: GNU GENERAL PUBLIC LICENSE
